CHANGELOG
LICENSE
MANIFEST.in
README.md
WAIVER
WAIVER.asc
requirements.txt
setup.cfg
setup.py
test_requirements.txt
chainlib/eth/address.py
chainlib/eth/block.py
chainlib/eth/chain.py
chainlib/eth/connection.py
chainlib/eth/constant.py
chainlib/eth/contract.py
chainlib/eth/error.py
chainlib/eth/gas.py
chainlib/eth/jsonrpc.py
chainlib/eth/log.py
chainlib/eth/nonce.py
chainlib/eth/settings.py
chainlib/eth/sign.py
chainlib/eth/src.py
chainlib/eth/tx.py
chainlib/eth/cli/__init__.py
chainlib/eth/cli/arg.py
chainlib/eth/cli/config.py
chainlib/eth/cli/decode.py
chainlib/eth/cli/encode.py
chainlib/eth/cli/log.py
chainlib/eth/cli/rpc.py
chainlib/eth/cli/wallet.py
chainlib/eth/data/config/config.ini
chainlib/eth/dialect/__init__.py
chainlib/eth/dialect/openethereum.py
chainlib/eth/pytest/__init__.py
chainlib/eth/pytest/fixtures_chain.py
chainlib/eth/pytest/fixtures_ethtester.py
chainlib/eth/pytest/fixtures_signer.py
chainlib/eth/runnable/__init__.py
chainlib/eth/runnable/balance.py
chainlib/eth/runnable/block.py
chainlib/eth/runnable/checksum.py
chainlib/eth/runnable/count.py
chainlib/eth/runnable/decode.py
chainlib/eth/runnable/encode.py
chainlib/eth/runnable/flags.py
chainlib/eth/runnable/gas.py
chainlib/eth/runnable/get.py
chainlib/eth/runnable/info.py
chainlib/eth/runnable/raw.py
chainlib/eth/runnable/subscribe.py
chainlib/eth/runnable/wait.py
chainlib/eth/unittest/base.py
chainlib/eth/unittest/ethtester.py
chainlib_eth.egg-info/PKG-INFO
chainlib_eth.egg-info/SOURCES.txt
chainlib_eth.egg-info/dependency_links.txt
chainlib_eth.egg-info/entry_points.txt
chainlib_eth.egg-info/requires.txt
chainlib_eth.egg-info/top_level.txt
man/build/eth-balance.1
man/build/eth-count.1
man/build/eth-decode.1
man/build/eth-encode.1
man/build/eth-gas.1
man/build/eth-get.1
man/build/eth-info.1
man/build/eth-raw.1
man/build/eth-wait.1
tests/test_abi.py
tests/test_address.py
tests/test_block.py
tests/test_bloom.py
tests/test_cli.py
tests/test_event.py
tests/test_nonce.py
tests/test_sign.py
tests/test_stat.py
tests/test_tx.py