Metadata-Version: 2.1
Name: chainlib-eth
Version: 0.4.26
Summary: Ethereum implementation of the chainlib interface
Home-page: https://git.defalslfy.org/chainlib-eth
Author: Louis Holbrook
Author-email: dev@holbrook.no
License: AGPLv3+
Keywords: dlt,blockchain,cryptocurrency,ethereum
Classifier: Programming Language :: Python :: 3
Classifier: Operating System :: OS Independent
Classifier: Development Status :: 3 - Alpha
Classifier: Topic :: Software Development :: Libraries
Classifier: Environment :: Console
Classifier: Intended Audience :: Developers
Classifier: License :: OSI Approved :: GNU Affero General Public License v3 or later (AGPLv3+)
Classifier: Topic :: Internet
Requires-Python: <3.11,>=3.8
License-File: LICENSE
